{
    "merge": [
        {
            "paths": [],
            "path": ""
        }
    ],
    "rename": [
        {
            "glob": "mod1/102-3.webp",
            "path": "mod1/101-수정33.webp"
        },
        {
            "glob": "**/*.css",
            "dir": "css"
        },
        {
            "glob": "**/*.html",
            "dir": "web"
        },
        {
            "glob": "mod1/aaa/bbb",
            "dir": "vir/aaa"
        }
    ],
    "except": [
        "**/.*"
    ],
    "setup": [
        {
            "glob": "**/board.css",
            "refedType": 1

        }
    ],
    "global": {

    }
}