{
	".DS_Store": {
		"depend": {}
	},
	"100.webp": {
		"depend": {}
	},
	"102-3.webp": {
		"depend": {}
	},
	"board.css": {
		"depend": {
			"src/style.css": [
				{
					"idx": 13,
					"line": 1,
					"key": "../dep/M2-1/style.css"
				}
			]
		}
	},
	"m3.html": {
		"depend": {
			"src/102-3.webp": [],
			"src/board.css": [
				{
					"idx": 71,
					"line": 3,
					"key": "board.css"
				}
			],
			"src/m3.html": [
				{
					"idx": 119,
					"line": 6,
					"key": "m3.html"
				}
			],
			"src/m2.html": [
				{
					"idx": 341,
					"line": 12,
					"key": "/dep/M2-1/m2.html"
				}
			]
		}
	}
}